.gitignore
CHANGES.rst
LICENSE.GPL
LICENSE.txt
MANIFEST.in
README.rst
setup.py
maxclient/__init__.py
maxclient/client.py
maxclient/defaults.py
maxclient/resources.py
maxclient/rest.py
maxclient/tests.py
maxclient/utils.py
maxclient/wsgi.py
maxclient.egg-info/PKG-INFO
maxclient.egg-info/SOURCES.txt
maxclient.egg-info/dependency_links.txt
maxclient.egg-info/entry_points.txt
maxclient.egg-info/not-zip-safe
maxclient.egg-info/requires.txt
maxclient.egg-info/top_level.txt