Metadata-Version: 1.1
Name: maxclient
Version: 4.0.2
Summary: Client library wrapper to access MAX API.
Home-page: https://github.com/upcnet/maxclient
Author: UPCnet Plone Team
Author-email: plone.team@upcnet.es
License: UNKNOWN
Keywords: web pyramid pylons client
Platform: UNKNOWN
Classifier: Programming Language :: Python
